[
  {
    "timestamp": "1574247186.3972683",
    "feature_set": "1",
    "features": [
      {
        "column": "categories_0",
        "type": "categorical",
        "encoder": "one_hot",
        "na_strategy": "set:NA"
      },
      {
        "column": "country_origin",
        "type": "categorical",
        "encoder": "one_hot",
        "na_strategy": "set:NA"
      },
      {
        "column": "ico_data_country_origin",
        "type": "categorical",
        "encoder": "one_hot",
        "na_strategy": "set:NA"
      },
      {
        "column": "ico_data_hardcap_currency",
        "type": "categorical",
        "encoder": "one_hot",
        "na_strategy": "set:NA"
      },
      {
        "column": "ico_data_softcap_currency",
        "type": "categorical",
        "encoder": "one_hot",
        "na_strategy": "set:NA"
      },
      {
        "column": "ico_data_total_raised_currency",
        "type": "categorical",
        "encoder": "one_hot",
        "na_strategy": "set:NA"
      },
      {
        "column": "ico_data_country_origin",
        "type": "categorical",
        "encoder": "one_hot",
        "na_strategy": "set:NA"
      },
      {
        "column": "holder_count",
        "type": "numerical",
        "na_strategy": "median"
      },
      {
        "column": "transaction_count",
        "type": "numerical",
        "na_strategy": "mean"
      },
      {
        "column": "market_data_current_price_usd",
        "type": "numerical",
        "na_strategy": "mean"
      },
      {
        "column": "market_data_ath_usd",
        "type": "numerical",
        "na_strategy": "mean"
      },
      {
        "column": "market_data_total_supply",
        "type": "numerical",
        "na_strategy": "mean"
      },
      {
        "column": "market_data_circulating_supply",
        "type": "numerical",
        "na_strategy": "mean"
      },
      {
        "column": "market_data_high_24h_usd",
        "type": "numerical",
        "na_strategy": "mean"
      },
      {
        "column": "market_data_low_24h_usd",
        "type": "numerical",
        "na_strategy": "mean"
      },
      {
        "column": "public_interest_stats_bing_matches",
        "type": "numerical",
        "na_strategy": "mean"
      },
      {
        "column": "community_data_facebook_likes",
        "type": "numerical",
        "na_strategy": "mean"
      },
      {
        "column": "community_data_twitter_followers",
        "type": "numerical",
        "na_strategy": "mean"
      },
      {
        "column": "community_data_reddit_subscribers",
        "type": "numerical",
        "na_strategy": "mean"
      },
      {
        "column": "developer_data_stars",
        "type": "numerical",
        "na_strategy": "mean"
      },
      {
        "column": "developer_data_subscribers",
        "type": "numerical",
        "na_strategy": "mean"
      },
      {
        "column": "developer_data_total_issues",
        "type": "numerical",
        "na_strategy": "mean"
      },
      {
        "column": "developer_data_closed_issues",
        "type": "numerical",
        "na_strategy": "mean"
      },
      {
        "column": "developer_data_pull_requests_merged",
        "type": "numerical",
        "na_strategy": "mean"
      },
      {
        "column": "developer_data_commit_count_4_weeks",
        "type": "numerical",
        "na_strategy": "mean"
      },
      {
        "column": "ico_data_hardcap_amount",
        "type": "numerical",
        "na_strategy": "mean"
      },
      {
        "column": "ico_data_softcap_amount",
        "type": "numerical",
        "na_strategy": "mean"
      }
    ],
    "metrics": { "mcc": 0.1492800572678234 },
    "model_name": "lbm"
  },
  {
    "timestamp": "1574329485.95991",
    "feature_set": "1",
    "features": [
      {
        "column": "categories_0",
        "type": "categorical",
        "encoder": "one_hot",
        "na_strategy": "set:NA"
      },
      {
        "column": "country_origin",
        "type": "categorical",
        "encoder": "one_hot",
        "na_strategy": "set:NA"
      },
      {
        "column": "ico_data_country_origin",
        "type": "categorical",
        "encoder": "one_hot",
        "na_strategy": "set:NA"
      },
      {
        "column": "ico_data_hardcap_currency",
        "type": "categorical",
        "encoder": "one_hot",
        "na_strategy": "set:NA"
      },
      {
        "column": "ico_data_softcap_currency",
        "type": "categorical",
        "encoder": "one_hot",
        "na_strategy": "set:NA"
      },
      {
        "column": "ico_data_total_raised_currency",
        "type": "categorical",
        "encoder": "one_hot",
        "na_strategy": "set:NA"
      },
      {
        "column": "ico_data_country_origin",
        "type": "categorical",
        "encoder": "one_hot",
        "na_strategy": "set:NA"
      },
      {
        "column": "holder_count",
        "type": "numerical",
        "na_strategy": "median"
      },
      {
        "column": "transaction_count",
        "type": "numerical",
        "na_strategy": "mean"
      },
      {
        "column": "market_data_current_price_usd",
        "type": "numerical",
        "na_strategy": "mean"
      },
      {
        "column": "market_data_ath_usd",
        "type": "numerical",
        "na_strategy": "mean"
      },
      {
        "column": "market_data_total_supply",
        "type": "numerical",
        "na_strategy": "mean"
      },
      {
        "column": "market_data_circulating_supply",
        "type": "numerical",
        "na_strategy": "mean"
      },
      {
        "column": "market_data_high_24h_usd",
        "type": "numerical",
        "na_strategy": "mean"
      },
      {
        "column": "market_data_low_24h_usd",
        "type": "numerical",
        "na_strategy": "mean"
      },
      {
        "column": "public_interest_stats_bing_matches",
        "type": "numerical",
        "na_strategy": "mean"
      },
      {
        "column": "community_data_facebook_likes",
        "type": "numerical",
        "na_strategy": "mean"
      },
      {
        "column": "community_data_twitter_followers",
        "type": "numerical",
        "na_strategy": "mean"
      },
      {
        "column": "community_data_reddit_subscribers",
        "type": "numerical",
        "na_strategy": "mean"
      },
      {
        "column": "developer_data_stars",
        "type": "numerical",
        "na_strategy": "mean"
      },
      {
        "column": "developer_data_subscribers",
        "type": "numerical",
        "na_strategy": "mean"
      },
      {
        "column": "developer_data_total_issues",
        "type": "numerical",
        "na_strategy": "mean"
      },
      {
        "column": "developer_data_closed_issues",
        "type": "numerical",
        "na_strategy": "mean"
      },
      {
        "column": "developer_data_pull_requests_merged",
        "type": "numerical",
        "na_strategy": "mean"
      },
      {
        "column": "developer_data_commit_count_4_weeks",
        "type": "numerical",
        "na_strategy": "mean"
      },
      {
        "column": "ico_data_hardcap_amount",
        "type": "numerical",
        "na_strategy": "mean"
      },
      {
        "column": "ico_data_softcap_amount",
        "type": "numerical",
        "na_strategy": "mean"
      }
    ],
    "metrics": { "mcc": 0.1492800572678234 },
    "model_name": "lbm",
    "hyperparam": {
      "n_estimators": 2000,
      "learning_rate": 0.01,
      "num_leaves": 123,
      "colsample_bytree": 0.8,
      "subsample": 0.9,
      "max_depth": 15,
      "reg_alpha": 0.1,
      "reg_lambda": 0.1,
      "min_split_gain": 0.01,
      "min_child_weight": 2
    }
  },
  {
    "timestamp": "1574330537.7636187",
    "feature_set": "1",
    "features": [
      {
        "column": "categories_0",
        "type": "categorical",
        "encoder": "one_hot",
        "na_strategy": "set:NA"
      },
      {
        "column": "country_origin",
        "type": "categorical",
        "encoder": "one_hot",
        "na_strategy": "set:NA"
      },
      {
        "column": "ico_data_country_origin",
        "type": "categorical",
        "encoder": "one_hot",
        "na_strategy": "set:NA"
      },
      {
        "column": "ico_data_hardcap_currency",
        "type": "categorical",
        "encoder": "one_hot",
        "na_strategy": "set:NA"
      },
      {
        "column": "ico_data_softcap_currency",
        "type": "categorical",
        "encoder": "one_hot",
        "na_strategy": "set:NA"
      },
      {
        "column": "ico_data_total_raised_currency",
        "type": "categorical",
        "encoder": "one_hot",
        "na_strategy": "set:NA"
      },
      {
        "column": "ico_data_country_origin",
        "type": "categorical",
        "encoder": "one_hot",
        "na_strategy": "set:NA"
      },
      {
        "column": "holder_count",
        "type": "numerical",
        "na_strategy": "median"
      },
      {
        "column": "transaction_count",
        "type": "numerical",
        "na_strategy": "mean"
      },
      {
        "column": "market_data_current_price_usd",
        "type": "numerical",
        "na_strategy": "mean"
      },
      {
        "column": "market_data_ath_usd",
        "type": "numerical",
        "na_strategy": "mean"
      },
      {
        "column": "market_data_total_supply",
        "type": "numerical",
        "na_strategy": "mean"
      },
      {
        "column": "market_data_circulating_supply",
        "type": "numerical",
        "na_strategy": "mean"
      },
      {
        "column": "market_data_high_24h_usd",
        "type": "numerical",
        "na_strategy": "mean"
      },
      {
        "column": "market_data_low_24h_usd",
        "type": "numerical",
        "na_strategy": "mean"
      },
      {
        "column": "public_interest_stats_bing_matches",
        "type": "numerical",
        "na_strategy": "mean"
      },
      {
        "column": "community_data_facebook_likes",
        "type": "numerical",
        "na_strategy": "mean"
      },
      {
        "column": "community_data_twitter_followers",
        "type": "numerical",
        "na_strategy": "mean"
      },
      {
        "column": "community_data_reddit_subscribers",
        "type": "numerical",
        "na_strategy": "mean"
      },
      {
        "column": "developer_data_stars",
        "type": "numerical",
        "na_strategy": "mean"
      },
      {
        "column": "developer_data_subscribers",
        "type": "numerical",
        "na_strategy": "mean"
      },
      {
        "column": "developer_data_total_issues",
        "type": "numerical",
        "na_strategy": "mean"
      },
      {
        "column": "developer_data_closed_issues",
        "type": "numerical",
        "na_strategy": "mean"
      },
      {
        "column": "developer_data_pull_requests_merged",
        "type": "numerical",
        "na_strategy": "mean"
      },
      {
        "column": "developer_data_commit_count_4_weeks",
        "type": "numerical",
        "na_strategy": "mean"
      },
      {
        "column": "ico_data_hardcap_amount",
        "type": "numerical",
        "na_strategy": "mean"
      },
      {
        "column": "ico_data_softcap_amount",
        "type": "numerical",
        "na_strategy": "mean"
      }
    ],
    "metrics": { "mcc": 0.1492800572678234 },
    "model_name": "lbm",
    "hyperparam": {
      "n_estimators": 2000,
      "learning_rate": 0.01,
      "num_leaves": 123,
      "colsample_bytree": 0.8,
      "subsample": 0.9,
      "max_depth": 15,
      "reg_alpha": 0.1,
      "reg_lambda": 0.1,
      "min_split_gain": 0.01,
      "min_child_weight": 2
    },
    "submission": "15"
  }
]
